vufr/__init__.py
vufr/vufr.py
vufr-1.5.1.dist-info/METADATA
vufr-1.5.1.dist-info/WHEEL
vufr-1.5.1.dist-info/top_level.txt
vufr-1.5.1.dist-info/RECORD
